pyfglt-0.3.0.dist-info/METADATA
pyfglt-0.3.0.dist-info/WHEEL
pyfglt/_fglt_c.cp311-win_amd64.pyd
pyfglt/_fglt_c.cp311-win_amd64.dll.a
pyfglt/fglt.py
pyfglt/__init__.py
pyfglt-0.3.0.data/headers/fglt.hpp
pyfglt-0.3.0.dist-info/RECORD
