Metadata-Version: 2.1
Name: pyfglt
Version: 0.3.0
Summary: Python package/wrapper of Fast Graphlet Transform
Author: Dimitris Floros
License: Apache-2.0
Classifier: License :: OSI Approved :: Apache Software License
Project-URL: Homepage, https://github.com/fcdimitr/pyfglt
Project-URL: Changelog, https://github.com/fcdimitr/pyfglt/releases
Project-URL: Issues, https://github.com/fcdimitr/pyfglt/issues
Project-URL: CI, https://github.com/fcdimitr/pyfglt/actions
Project-URL: Documentation, https://fcdimitr.github.io/pyfglt/
Requires-Python: >=3.8
Requires-Dist: numpy>=1.19.5
Requires-Dist: scipy>=1.7.3
Requires-Dist: pandas>=2.2.0
Requires-Dist: networkx>=3.2.1
Requires-Dist: typeguard>=4.4.1
Provides-Extra: test
Requires-Dist: pytest; extra == "test"
Provides-Extra: docs
Requires-Dist: mkdocs-material>=9.5.50; extra == "docs"
Requires-Dist: mkdocstrings>=0.27.0; extra == "docs"
Requires-Dist: mkdocstrings-python>=1.13.0; extra == "docs"
Requires-Dist: matplotlib>=3.10.0; extra == "docs"
Requires-Dist: jupyter>=1.1.1; extra == "docs"
Requires-Dist: tabulate>=0.9.0; extra == "docs"
Requires-Dist: seaborn>=0.13.2; extra == "docs"
